dnachisel_dtailor_mode/Design.py
dnachisel_dtailor_mode/DnaDesignProblem.py
dnachisel_dtailor_mode/SequenceDesigner.py
dnachisel_dtailor_mode/__init__.py
dnachisel_dtailor_mode/version.py
dnachisel_dtailor_mode/tools/DBSQLite.py
dnachisel_dtailor_mode/tools/__init__.py
dnachisel_dtailor_mode/tools/biotables_tailor.py
dnachisel_dtailor_mode/tools/codontools.py
dnachisel_dtailor_mode/tools/mathtools.py
dnachisel_dtailor_mode/tools/range.py
dnachisel_dtailor_mode/tools/seqtools.py
dnachisel_dtailor_mode/tools/tailor_example.py
dnachisel_dtailor_mode-0.1.1.dist-info/METADATA
dnachisel_dtailor_mode-0.1.1.dist-info/WHEEL
dnachisel_dtailor_mode-0.1.1.dist-info/top_level.txt
dnachisel_dtailor_mode-0.1.1.dist-info/RECORD
