Metadata-Version: 2.1
Name: dnachisel-dtailor-mode
Version: 0.1.1
Summary: implement d-tailor method using dnachisel specs
Home-page: https://github.com/Lix1993/dnachisel_dtailor_mode
Author: Li Xing
Author-email: lix930701@gmail.com
License: UNKNOWN
Platform: UNKNOWN
Classifier: Programming Language :: Python :: 3
Classifier: License :: OSI Approved :: MIT License
Classifier: Operating System :: OS Independent
Requires-Python: >=3.6
